muxtools/__init__.py
muxtools/__main__.py
muxtools/_version.py
muxtools/cli.py
muxtools/functions.py
muxtools/main.py
muxtools/py.typed
muxtools/audio/__init__.py
muxtools/audio/audioutils.py
muxtools/audio/encoders.py
muxtools/audio/extractors.py
muxtools/audio/memecoders.py
muxtools/audio/preprocess.py
muxtools/audio/tools.py
muxtools/helpers/__init__.py
muxtools/helpers/helper_util.py
muxtools/helpers/propedit.py
muxtools/helpers/bsf/__init__.py
muxtools/helpers/bsf/bsf_generic.py
muxtools/helpers/bsf/bsf_hevc_avc.py
muxtools/helpers/bsf/bsf_mpeg2.py
muxtools/misc/__init__.py
muxtools/misc/chapters.py
muxtools/muxing/__init__.py
muxtools/muxing/muxer.py
muxtools/muxing/muxfiles.py
muxtools/muxing/tmdb.py
muxtools/muxing/token_handling.py
muxtools/muxing/tracks.py
muxtools/subtitle/__init__.py
muxtools/subtitle/basesub.py
muxtools/subtitle/font.py
muxtools/subtitle/styles.py
muxtools/subtitle/sub.py
muxtools/subtitle/sub_pgs.py
muxtools/subtitle/subutils.py
muxtools/utils/__init__.py
muxtools/utils/convert.py
muxtools/utils/dataclass.py
muxtools/utils/download.py
muxtools/utils/env.py
muxtools/utils/files.py
muxtools/utils/formats.py
muxtools/utils/glob.py
muxtools/utils/language_util.py
muxtools/utils/log.py
muxtools/utils/parsing.py
muxtools/utils/probe.py
muxtools/utils/subprogress.py
muxtools/utils/types.py
muxtools-0.4.1.dist-info/METADATA
muxtools-0.4.1.dist-info/WHEEL
muxtools-0.4.1.dist-info/entry_points.txt
muxtools-0.4.1.dist-info/licenses/LICENSE
muxtools-0.4.1.dist-info/RECORD
